ezgame/__init__.py
ezgame/animations.py
ezgame/main.py
ezgame/premade.py
ezsgame-0.0.dist-info/METADATA
ezsgame-0.0.dist-info/WHEEL
ezsgame-0.0.dist-info/top_level.txt
ezsgame-0.0.dist-info/RECORD
