Metadata-Version: 2.1
Name: ezsgame
Version: 0.0
Summary: En general ezgame Trata de hacer mas simple el proceso de Creacion y manipulacion de graficos 2D.
Home-page: UNKNOWN
Author: Hendrick Y. "NoVa
Author-email: hendrickrodriguez.nova@gmail.com
License: MIT
Platform: UNKNOWN
Requires-Dist: pygame
